ydf/__init__.py
ydf/api_test.py
ydf/version.py
ydf/api/__init__.py
ydf/api/experimental.py
ydf/api/help.py
ydf/api/internal.py
ydf/api/util.py
ydf/cc/__init__.py
ydf/cc/ydf.so
ydf/dataset/__init__.py
ydf/dataset/dataset.py
ydf/dataset/dataset_test.py
ydf/dataset/dataset_with_tf_test.py
ydf/dataset/dataspec.py
ydf/dataset/dataspec_test.py
ydf/dataset/io/__init__.py
ydf/dataset/io/dataset_io.py
ydf/dataset/io/dataset_io_test.py
ydf/dataset/io/dataset_io_types.py
ydf/dataset/io/generator.py
ydf/dataset/io/numpy_io.py
ydf/dataset/io/numpy_io_test.py
ydf/dataset/io/pandas_io.py
ydf/dataset/io/pandas_io_test.py
ydf/dataset/io/polars_io.py
ydf/dataset/io/polars_io_test.py
ydf/dataset/io/pygrain_io.py
ydf/dataset/io/pygrain_io_test.py
ydf/dataset/io/tensorflow_io.py
ydf/dataset/io/xarray_io.py
ydf/dataset/io/xarray_io_test.py
ydf/deep/__init__.py
ydf/deep/analysis.py
ydf/deep/analysis_test.py
ydf/deep/dataset.py
ydf/deep/dataset_test.py
ydf/deep/generic_jax.py
ydf/deep/hyperparameter.py
ydf/deep/hyperparameter_test.py
ydf/deep/jax_fallback.py
ydf/deep/layer.py
ydf/deep/layer_test.py
ydf/deep/metric.py
ydf/deep/metric_test.py
ydf/deep/mlp.py
ydf/deep/mlp_test.py
ydf/deep/model_lib.py
ydf/deep/preprocessor.py
ydf/deep/preprocessor_test.py
ydf/deep/safetensors.py
ydf/deep/safetensors_test.py
ydf/deep/tabular_transformer.py
ydf/deep/tabular_transformer_test.py
ydf/learner/__init__.py
ydf/learner/abstract_feature_selector.py
ydf/learner/cart_learner_test.py
ydf/learner/custom_loss.py
ydf/learner/custom_loss_test.py
ydf/learner/distributed_learner_test.py
ydf/learner/feature_selector.py
ydf/learner/feature_selector_test.py
ydf/learner/generic_learner.py
ydf/learner/generic_learner_test.py
ydf/learner/gradient_boosted_trees_learner_test.py
ydf/learner/hyperparameters.py
ydf/learner/hyperparameters_test.py
ydf/learner/isolation_forest_learner_test.py
ydf/learner/learner_test_utils.py
ydf/learner/learner_with_tf_test.py
ydf/learner/learner_with_xarray_test.py
ydf-0.13.0.dist-info/licenses/LICENSE
ydf-0.13.0.dist-info/METADATA
ydf-0.13.0.dist-info/WHEEL
ydf-0.13.0.dist-info/top_level.txt
ydf-0.13.0.dist-info/RECORD
