Metadata-Version: 2.1
Name: ydf
Version: 0.13.0
Summary: YDF (short for Yggdrasil Decision Forests) is a library for training, serving, evaluating and analyzing decision forest models such as Random Forest and Gradient Boosted Trees.
Home-page: https://github.com/google/yggdrasil-decision-forests
Author: Mathieu Guillame-Bert, Richard Stotz, Jan Pfeifer
Author-email: decision-forests-contact@google.com
License: Apache 2.0
Project-URL: Documentation, https://ydf.readthedocs.io/
Project-URL: Source, https://github.com/google/yggdrasil-decision-forests.git
Project-URL: Tracker, https://github.com/google/yggdrasil-decision-forests/issues
Keywords: machine learning decision forests random forest gradient boosted decision trees CART isolation forests classification regression  ranking uplift
Classifier: Intended Audience :: Developers
Classifier: Intended Audience :: Education
Classifier: Intended Audience :: Science/Research
Classifier: License :: OSI Approved :: Apache Software License
Classifier: Programming Language :: Python :: 3
Classifier: Programming Language :: Python :: 3.8
Classifier: Programming Language :: Python :: 3.9
Classifier: Programming Language :: Python :: 3.10
Classifier: Programming Language :: Python :: 3.11
Classifier: Programming Language :: Python :: 3.12
Classifier: Programming Language :: Python :: 3.13
Classifier: Programming Language :: Python :: 3 :: Only
Classifier: Topic :: Scientific/Engineering
Classifier: Topic :: Scientific/Engineering :: Mathematics
Classifier: Topic :: Scientific/Engineering :: Artificial Intelligence
Classifier: Topic :: Software Development
Classifier: Topic :: Software Development :: Libraries
Classifier: Topic :: Software Development :: Libraries :: Python Modules
Requires-Python: >=3.8
License-File: LICENSE
Requires-Dist: numpy
Requires-Dist: absl-py
Requires-Dist: protobuf <7.0.0,>=5.29.1
Provides-Extra: pandas
Requires-Dist: pandas ; extra == 'pandas'
